odoo/addons/so_sequence_duplicate_order/README.rst
odoo/addons/so_sequence_duplicate_order/__init__.py
odoo/addons/so_sequence_duplicate_order/__manifest__.py
odoo/addons/so_sequence_duplicate_order/i18n/es.po
odoo/addons/so_sequence_duplicate_order/models/__init__.py
odoo/addons/so_sequence_duplicate_order/models/res_company.py
odoo/addons/so_sequence_duplicate_order/models/res_config_settings.py
odoo/addons/so_sequence_duplicate_order/models/sale_order.py
odoo/addons/so_sequence_duplicate_order/static/description/icon.png
odoo/addons/so_sequence_duplicate_order/views/res_config_settings_view.xml
odoo_addon_so_sequence_duplicate_order-15.0.1.0.1.2.dist-info/METADATA
odoo_addon_so_sequence_duplicate_order-15.0.1.0.1.2.dist-info/WHEEL
odoo_addon_so_sequence_duplicate_order-15.0.1.0.1.2.dist-info/top_level.txt
odoo_addon_so_sequence_duplicate_order-15.0.1.0.1.2.dist-info/RECORD
